setup.cfg
setup.py
tbapy/__init__.py
tbapy/main.py
tbapy/models.py
tbapy.egg-info/PKG-INFO
tbapy.egg-info/SOURCES.txt
tbapy.egg-info/dependency_links.txt
tbapy.egg-info/not-zip-safe
tbapy.egg-info/requires.txt
tbapy.egg-info/top_level.txt