Metadata-Version: 1.0
Name: tbapy
Version: 1.0.0
Summary: Python library to get data from The Blue Alliance API v3.
Home-page: https://github.com/frc1418/tbapy
Author: FRC Team 1418, Erik Boesen
Author-email: robotics1418@gmail.com
License: MIT
Platform: UNKNOWN
